leukeleu_django_checks/__init__.py
leukeleu_django_checks/apps.py
leukeleu_django_checks/checks.py
leukeleu_django_checks/management/__init__.py
leukeleu_django_checks/management/commands/__init__.py
leukeleu_django_checks/management/commands/list_staff_users.py
leukeleu_django_checks/management/commands/list_superusers.py
leukeleu_django_checks-1.3.0.dist-info/licenses/LICENSE
leukeleu_django_checks-1.3.0.dist-info/WHEEL
leukeleu_django_checks-1.3.0.dist-info/METADATA
leukeleu_django_checks-1.3.0.dist-info/RECORD
