Metadata-Version: 2.4
Name: leukeleu_django_checks
Version: 1.3.0
Summary: Additional deploy checks and other tools to validate if a Django project is set up correctly.
Author: Jaap Roes
Author-email: Jaap Roes <jroes@leukeleu.nl>
License-Expression: MIT
License-File: LICENSE
Classifier: License :: OSI Approved :: MIT License
Classifier: Development Status :: 5 - Production/Stable
Classifier: Framework :: Django
Classifier: Intended Audience :: Developers
Classifier: Programming Language :: Python :: 3
Requires-Dist: django>=4.2,<6
Requires-Python: >=3.10
Project-URL: Issues, https://github.com/leukeleu/leukeleu-django-checks/issues
Project-URL: Releasenotes, https://github.com/leukeleu/leukeleu-django-checks/releases
Project-URL: Repository, https://github.com/leukeleu/leukeleu-django-checks/
